<?xml version="1.0" encoding="UTF-8" standalone="yes"?>
<addons>
<addon id="plugin.program.browser.launcher" name="Browser Launcher" version="1.2.4" provider-name="AddonScriptorDE + Sandmann79">
    <requires>
        <import addon="xbmc.python" version="2.1.0"/>
    </requires>
    <extension point="xbmc.python.pluginsource" library="default.py">
        <provides>executable</provides>
    </extension>
    <extension point="xbmc.addon.metadata">
        <platform>all</platform>
        <summary lang="en">Browser Launcher</summary>
        <language></language>
        <description lang="en">Launch websites via selected Browser in Kiosk-mode</description>
        <description lang="de">Öffnet Websiten mit dem ausgewählten Browser im Vollbildmodus</description>
        <license>GNU GENERAL PUBLIC LICENSE. Version 2, June 1991</license>
        <email>AddonScriptorDE at yahoo dot de</email>
        <website></website>
    </extension>
</addon>
<addon id="plugin.video.amazon"
       name="Amazon"
       version="1.8.7"
       provider-name="Sandmann79 + BlueCop + Romans I XVI">
  <requires>
    <import addon="xbmc.python" version="2.24.0"/>
    <import addon="script.module.beautifulsoup" version="3.2.1"/>
    <import addon="script.module.mechanize" version="0.2.6"/>
    <import addon="script.module.amazon.database" version="0.1.1"/>
    <import addon="script.module.pydes" version="2.0.1"/>
    <import addon="script.module.pyxbmct" version="1.1.7"/>
    <import addon="script.module.myconnpy" version="1.1.7"/>
  </requires>
  <extension point="xbmc.python.pluginsource"
             library="default.py">
	<provides>video</provides>
  </extension>
  <extension point="xbmc.service" library="service.py" start="startup" />
  <extension point="xbmc.addon.metadata">
    <platform>all</platform>
    <summary lang="en">Amazon Prime Video Streaming</summary>
    <summary lang="de">Amazon Prime Instant Video</summary>
    <description lang="en">Movies and Television Shows for German Prime Members.
This Addon works only with German Amazon Accounts. For Non-German Accounts use Amazon VOD Addon from my repo.</description>
    <description lang="de">Filme und Serien für Amazon Prime Mitglieder</description>
    <disclaimer lang="en">Some parts of this addon may not be legal in your country of residence - please check with your local laws before installing.
This Addon uses pyDes by Todd Whiteman</disclaimer>
    <disclaimer lang="de">Möglicherweise sind einge Teile dieses Addons in Ihrem Land illegal, Sie sollten dies unbedingt vor der Installation überprüfen.
Diese Addon verwendet pyDes von Todd Whiteman</disclaimer>
    <license>GNU GENERAL PUBLIC LICENSE. Version 2, June 1991</license>
    <forum>http://www.kodinerds.net/index.php/Thread/44211-Release-Amazon-Prime-Instant-Video</forum>
    <source>https://github.com/Sandmann79/xbmc</source>    
  </extension>
</addon>
<addon id="plugin.video.amazon-test"
       name="Amazon VOD"
       version="0.4.2"
       provider-name="Sandmann79">
  <requires>
    <import addon="xbmc.python" version="2.24.0"/>
    <import addon="script.module.beautifulsoup" version="3.2.1"/>
    <import addon="script.module.mechanize" version="0.2.6"/>
    <import addon="script.module.pydes" version="2.0.1"/>
    <import addon="script.module.pyxbmct" version="1.1.7"/>
  </requires>
  <extension point="xbmc.python.pluginsource"
             library="default.py">
	<provides>video</provides>
  </extension>
  <extension point="xbmc.addon.metadata">
    <platform>all</platform>
    <summary lang="en">Amazon Prime Video Streaming</summary>
    <summary lang="de">Amazon Prime Instant Video</summary>
    <description lang="en">Movies and Television Shows for Prime Members</description>
    <description lang="de">Filme und Serien für Amazon Prime Mitglieder</description>
    <disclaimer lang="en">Some parts of this addon may not be legal in your country of residence - please check with your local laws before installing.
This Addon uses pyDes by Todd Whiteman</disclaimer>
    <disclaimer lang="de">Möglicherweise sind einge Teile dieses Addons in Ihrem Land illegal, Sie sollten dies unbedingt vor der Installation überprüfen.
Diese Addon verwendet pyDes von Todd Whiteman</disclaimer>
     <license>GNU GENERAL PUBLIC LICENSE. Version 2, June 1991</license>
    <forum>http://www.kodinerds.net/index.php/Thread/44211-Release-Amazon-Prime-Instant-Video</forum>
    <source>https://github.com/Sandmann79/xbmc</source>
  </extension>
</addon>
<addon id="repository.sandmann79.plugins" name="Sandmann79s Repository" version="1.0.2" provider-name="Sandmann79">
	<extension point="xbmc.addon.repository" name="Sandmann79s Repository">
		<info compressed="false">https://raw.githubusercontent.com/Sandmann79/xbmc/master/packages/addons.xml</info>
		<checksum>https://raw.githubusercontent.com/Sandmann79/xbmc/master/packages/addons.xml.md5</checksum>
		<datadir zip="true">https://raw.githubusercontent.com/Sandmann79/xbmc/master/packages/</datadir>
	</extension>
	<extension point="xbmc.addon.metadata">
		<summary>Test Repo</summary>
		<description></description>
		<disclaimer></disclaimer>
		<platform>all</platform>
	</extension>
</addon>
<addon id="script.module.amazon.database"
       name="Amazon Database"
       version="0.1.1"
       provider-name="BlueCop">
  <requires>
    <import addon="xbmc.python" version="2.1.0"/>
  </requires>
  <extension point="xbmc.python.module" 
             library="lib" /> 
  <extension point="xbmc.addon.metadata">
    <platform>all</platform>
  </extension>
</addon>
<addon id="script.module.pydes"
       name="pyDes"
       version="2.0.1"
       provider-name="Todd Whiteman">
  <requires>
    <import addon="xbmc.python" version="2.1.0"/>
  </requires>
  <extension point="xbmc.python.module"
             library="lib" />
  <extension point="xbmc.addon.metadata">
    <summary lang="en">A pure python module which implements the DES and Triple-DES encryption algorithms.</summary>
    <website>http://twhiteman.netfirms.com/des.html</website> 
    <license>Public Domain</license> 
    <platform>all</platform> 
    <source>http://sourceforge.net/projects/pydes/</source> 
  </extension>
</addon>
</addons>
